shelephant/__init__.py
shelephant/_remove.py
shelephant/_tests.py
shelephant/_version.py
shelephant/cli.py
shelephant/compute_hash.py
shelephant/convert.py
shelephant/dataset.py
shelephant/external.py
shelephant/local.py
shelephant/output.py
shelephant/path.py
shelephant/rsync.py
shelephant/scp.py
shelephant/search.py
shelephant/ssh.py
shelephant/yaml.py
shelephant-0.24.2.dist-info/LICENSE
shelephant-0.24.2.dist-info/METADATA
shelephant-0.24.2.dist-info/WHEEL
shelephant-0.24.2.dist-info/entry_points.txt
shelephant-0.24.2.dist-info/top_level.txt
shelephant-0.24.2.dist-info/RECORD
