Metadata-Version: 2.1
Name: shelephant
Version: 0.24.2
Summary: Simple dataset management
Author-email: Tom de Geus <tom@geus.me>
Project-URL: Source, https://github.com/tdegeus/shelephant
Classifier: License :: OSI Approved :: MIT License
Requires-Python: >=3.10
License-File: LICENSE
Requires-Dist: click
Requires-Dist: numpy >=1.15.0
Requires-Dist: platformdirs
Requires-Dist: prettytable
Requires-Dist: pyyaml
Requires-Dist: tqdm
